trivval/__init__.py
trivval/py.typed
trivval-1.1.2.dist-info/METADATA
trivval-1.1.2.dist-info/WHEEL
trivval-1.1.2.dist-info/top_level.txt
trivval-1.1.2.dist-info/zip-safe
trivval-1.1.2.dist-info/RECORD
