Metadata-Version: 2.1
Name: trivval
Version: 1.1.2
Summary: A library for trivial structure validation
Home-page: https://gitlab.com/ppentchev/python-trivval
Author: Peter Pentchev
Author-email: roam@ringlet.net
License: Apache License 2.0
Keywords: validate validation schema
Classifier: Development Status :: 5 - Production/Stable
Classifier: Intended Audience :: Developers
Classifier: License :: DFSG approved
Classifier: License :: Freely Distributable
Classifier: License :: OSI Approved :: BSD License
Classifier: Operating System :: OS Independent
Classifier: Programming Language :: Python
Classifier: Programming Language :: Python :: 3
Classifier: Programming Language :: Python :: 3.7
Classifier: Programming Language :: Python :: 3.8
Classifier: Programming Language :: Python :: 3.9
Classifier: Programming Language :: Python :: 3.10
Classifier: Programming Language :: Python :: 3.11
Classifier: Programming Language :: Python :: 3.12
Classifier: Topic :: Software Development :: Libraries
Classifier: Topic :: Software Development :: Libraries :: Python Modules
Classifier: Typing :: Typed
Requires-Python: >=3.7
